victorforever/__init__.py
victorforever-1.0.1.dist-info/METADATA
victorforever-1.0.1.dist-info/WHEEL
victorforever-1.0.1.dist-info/entry_points.txt
victorforever-1.0.1.dist-info/top_level.txt
victorforever-1.0.1.dist-info/RECORD
